mlcommons_box_k8s/__init__.py
mlcommons_box_k8s/k8s_run.py
mlcommons_box_k8s/main.py
mlcommons_box_k8s/tests/__init__.py
mlcommons_box_k8s/tests/test_mlcommons_box_k8s_cli.py
mlcommons_box_k8s/tests/test_mlcommons_box_k8s_run.py
mlcommons_box_k8s/tests/test_data/test_box/mlbox.yaml
mlcommons_box_k8s/tests/test_data/test_box/platforms/docker.yaml
mlcommons_box_k8s/tests/test_data/test_box/run/kubernetes.yaml
mlcommons_box_k8s-0.2.3.dist-info/METADATA
mlcommons_box_k8s-0.2.3.dist-info/WHEEL
mlcommons_box_k8s-0.2.3.dist-info/entry_points.txt
mlcommons_box_k8s-0.2.3.dist-info/top_level.txt
mlcommons_box_k8s-0.2.3.dist-info/RECORD
